universal_mcp_domain_checker/README.md
universal_mcp_domain_checker/__init__.py
universal_mcp_domain_checker/app.py
universal_mcp_domain_checker/server.py
universal_mcp_domain_checker-0.1.1.dist-info/METADATA
universal_mcp_domain_checker-0.1.1.dist-info/WHEEL
universal_mcp_domain_checker-0.1.1.dist-info/entry_points.txt
universal_mcp_domain_checker-0.1.1.dist-info/licenses/LICENSE
universal_mcp_domain_checker-0.1.1.dist-info/RECORD
